cachetronomy/__init__.py
cachetronomy/__main__.py
cachetronomy/py.typed
cachetronomy/core/__init__.py
cachetronomy/core/access_frequency.py
cachetronomy/core/serialization.py
cachetronomy/core/cache/__init__.py
cachetronomy/core/cache/cachetronaut.py
cachetronomy/core/eviction/__init__.py
cachetronomy/core/eviction/memory.py
cachetronomy/core/eviction/time_to_live.py
cachetronomy/core/store/__init__.py
cachetronomy/core/store/memory.py
cachetronomy/core/store/protocols.py
cachetronomy/core/store/sqlite/__init__.py
cachetronomy/core/store/sqlite/synchronous.py
cachetronomy/core/store/utils/__init__.py
cachetronomy/core/store/utils/batch_logger.py
cachetronomy/core/store/utils/sanitizers.py
cachetronomy/core/types/__init__.py
cachetronomy/core/types/profiles.py
cachetronomy/core/types/schemas.py
cachetronomy/core/types/settings.py
cachetronomy/core/utils/__init__.py
cachetronomy/core/utils/key_builder.py
cachetronomy/core/utils/time_utils.py
cachetronomy-0.3.2.dist-info/METADATA
cachetronomy-0.3.2.dist-info/WHEEL
cachetronomy-0.3.2.dist-info/entry_points.txt
cachetronomy-0.3.2.dist-info/licenses/LICENSE
cachetronomy-0.3.2.dist-info/licenses/LICENSE-msgpack.txt
cachetronomy-0.3.2.dist-info/RECORD
