Metadata-Version: 2.4
Name: cachetronomy
Version: 0.3.2
Summary: A lightweight, SQLite-backed cache for Python with first-class sync and async support.
Project-URL: Homepage, https://github.com/cachetronaut/cachetronomy
Project-URL: Issues, https://github.com/cachetronaut/cachetronomy/issues
Project-URL: Documentation, https://github.com/cachetronaut/cachetronomy
Project-URL: Repository, https://github.com/cachetronaut/cachetronomy
Author-email: Abraham Castro-Vela <abrahamacastro+code@gmail.com>
License: MIT License
License-File: LICENSE
License-File: LICENSE-msgpack.txt
Keywords: async,background-eviction,cache,cache-invalidation,caching,cli,decorator,eviction,function,functions,hot-key-tracking,json,lfu,local,memoisation,memoise,memoization,memoize,memory,memory-pressure,mfu,msgpack,optimisation,optimise,optimization,optimize,optimizing,orjson,performance,persistence,persistent,pluggable-serialization,profile,profiles,python,serialization,sql,sqlite,stats,sync,tags,time-to-live,ttl
Classifier: Development Status :: 4 - Beta
Classifier: Environment :: Console
Classifier: Framework :: AsyncIO
Classifier: Framework :: Pydantic
Classifier: Framework :: Pydantic :: 2
Classifier: Intended Audience :: Developers
Classifier: Intended Audience :: Information Technology
Classifier: Intended Audience :: System Administrators
Classifier: License :: OSI Approved :: MIT License
Classifier: Operating System :: OS Independent
Classifier: Programming Language :: Python :: 3
Classifier: Programming Language :: Python :: 3 :: Only
Classifier: Programming Language :: Python :: 3.10
Classifier: Programming Language :: Python :: 3.11
Classifier: Programming Language :: Python :: 3.12
Classifier: Programming Language :: Python :: 3.13
Classifier: Topic :: Software Development
Classifier: Topic :: Software Development :: Libraries
Classifier: Topic :: Software Development :: Libraries :: Python Modules
Classifier: Topic :: System :: Distributed Computing
Classifier: Topic :: System :: Monitoring
Classifier: Topic :: Utilities
Classifier: Typing :: Typed
Requires-Python: <4.0,>=3.10
Requires-Dist: psutil<8.0,>=5.9
Requires-Dist: pydantic-settings<3.0,>=2.0
Requires-Dist: pydantic<3.0,>=2.0
Requires-Dist: python-dateutil<3.0,>=2.8
Requires-Dist: python-dotenv>=1.1.0
Requires-Dist: pyyaml<7.0,>=6.0
Requires-Dist: rich>=14.0.0
Requires-Dist: synchronaut[fast]>=0.3.5
Requires-Dist: typer>=0.16.0
Requires-Dist: typing-extensions>=4.13.2
Provides-Extra: dev
Requires-Dist: pytest-asyncio>=0.26.0; extra == 'dev'
Requires-Dist: pytest>=8.3.5; extra == 'dev'
Provides-Extra: fast
Requires-Dist: msgpack>=1.1.0; extra == 'fast'
Requires-Dist: orjson>=3.10.16; extra == 'fast'
Provides-Extra: lint
Requires-Dist: ruff>=0.11.11; extra == 'lint'
